Metadata-Version: 2.1
Name: association-metrics
Version: 0.0.1
Summary: Python module for measure the degree of association between variables
Home-page: https://github.com/HeberTU/association_metrics
Author: Heber Trujillo
Author-email: heber.trj.urt@gmail.com
License: UNKNOWN
Platform: UNKNOWN
Classifier: Programming Language :: Python :: 3
Classifier: License :: OSI Approved :: MIT License
Classifier: Operating System :: OS Independent
Requires-Python: >=3.6
